MANIFEST.in
README.md
setup.cfg
setup.py
bubbletools/__init__.py
bubbletools/__main__.py
bubbletools/_bubble.py
bubbletools/_gexf.py
bubbletools/_js.py
bubbletools/_js_data.py
bubbletools/bbltree.py
bubbletools/comparers.py
bubbletools/converter.py
bubbletools/info.py
bubbletools/utils.py
bubbletools/validator.py
bubbletools.egg-info/PKG-INFO
bubbletools.egg-info/SOURCES.txt
bubbletools.egg-info/dependency_links.txt
bubbletools.egg-info/not-zip-safe
bubbletools.egg-info/requires.txt
bubbletools.egg-info/top_level.txt
bubbletools/_js_dir_template/index.html
bubbletools/_js_dir_template/style.css
bubbletools/_js_dir_template/js/cytoscape-cose-bilkent.js
bubbletools/_js_dir_template/js/cytoscape.min.js
bubbletools/test/__init__.py
bubbletools/test/test_bbltree.py
bubbletools/test/test_utils.py
bubbletools/test/test_validator.py