Metadata-Version: 1.1
Name: bubbletools
Version: 0.6.10
Summary: Tools around the bubble format
Home-page: https://github.com/aluriak/bubble-tools
Author: Lucas Bourneuf
Author-email: lucas.bourneuf@laposte.net
License: GPL
Keywords: graph,format
Platform: UNKNOWN
Classifier: Development Status :: 4 - Beta
Classifier: Intended Audience :: Science/Research
Classifier: License :: OSI Approved :: GNU General Public License (GPL)
Classifier: Natural Language :: English
Classifier: Programming Language :: Python :: 3
Classifier: Programming Language :: Python :: 3.5
Classifier: Programming Language :: Python :: 3.6
Classifier: Programming Language :: Python :: 3.7
Classifier: Topic :: Software Development :: Libraries :: Python Modules
